Workbook
Name Aport: 'Dio Invest'!$D$14:$D$14
Name Patrimonio: 'Dio Invest'!$D$17:$D$17
Name Qtde_Anos: 'Dio Invest'!$D$15:$D$15
Name Rendimento_Carteira: 'Dio Invest'!$D$10:$D$10
Name Salario: 'Dio Invest'!$D$9:$D$9
Name Tx_mensal: 'Dio Invest'!$D$16:$D$16

Sheet Auxiliar
B2: CHAVE | C2: PERFIL | D2: TIPO DE FII | E2: %
B3: =C3&"-"&D3 -> Conservador-PAPEL | C3: Conservador | D3: PAPEL | E3: 0.3
B4: =C4&"-"&D4 -> Conservador-TIJOLO | C4: Conservador | D4: TIJOLO | E4: 0.5
B5: =C5&"-"&D5 -> Conservador-HÍBRIDOS | C5: Conservador | D5: HÍBRIDOS | E5: 0.1
B6: =C6&"-"&D6 -> Conservador-FOFs | C6: Conservador | D6: FOFs | E6: 0.1
B7: =C7&"-"&D7 -> Conservador-DESENVOLVIMENTO | C7: Conservador | D7: DESENVOLVIMENTO | E7: 0
B8: =C8&"-"&D8 -> Conservador-HOTELARIAS | C8: Conservador | D8: HOTELARIAS | E8: 0
B9: =C9&"-"&D9 -> Moderado-PAPEL | C9: Moderado | D9: PAPEL | E9: 0.32
B10: =C10&"-"&D10 -> Moderado-TIJOLO | C10: Moderado | D10: TIJOLO | E10: 0.35
B11: =C11&"-"&D11 -> Moderado-HÍBRIDOS | C11: Moderado | D11: HÍBRIDOS | E11: 0.08
B12: =C12&"-"&D12 -> Moderado-FOFs | C12: Moderado | D12: FOFs | E12: 0.05
B13: =C13&"-"&D13 -> Moderado-DESENVOLVIMENTO | C13: Moderado | D13: DESENVOLVIMENTO | E13: 0.1
B14: =C14&"-"&D14 -> Moderado-HOTELARIAS | C14: Moderado | D14: HOTELARIAS | E14: 0.1
... B20: =C20&"-"&D20 -> Agressivo-HOTELARIAS | C20: Agressivo | D20: HOTELARIAS | E20: 0.1

Sheet Dio Invest
B8: CONFIGURAÇÕES
B9: Salário | D9: 5000
B10: Rendimento Carteira | D10: 0.01
B11: Sugestão de Investimento (30%) | D11: =D9*30% -> 1500
B13: INVESTIMENTO MENSAL
B14: Quanto investir por mês ? | D14: 500
B15: Por Quantos Anos ? | D15: 5
B16: Taxa de Rendimento mensal ? | D16: 0.01079
B17: Patrimônio acumulado ? | D17: {=FV(Tx_mensal,Qtde_Anos*12,Aport*-1)} -> 41888.457
B18: Dividendos Mensais ? | D18: {=Patrimonio*Rendimento_Carteira} -> 418.88457
B20: Cenários | D20: Dividendo
A21: 2 | B21: Quanto em 2 Anos ? | C21: =FV($D$16,$A21*12,$D$14*-1) -> 13613.814 | D21: {=C21*Rendimento_Carteira} -> 136.13814
A22: 5 | B22: Quanto em 5 Anos ? | C22: =FV($D$16,$A22*12,$D$14*-1) -> 41888.457 | D22: {=C22*Rendimento_Carteira} -> 418.88457
A23: 10 | B23: Quanto em 10 Anos ? | C23: =FV($D$16,$A23*12,$D$14*-1) -> 121642.11 | D23: {=C23*Rendimento_Carteira} -> 1216.4211
A24: 20 | B24: Quanto em 20 Anos ? | C24: =FV($D$16,$A24*12,$D$14*-1) -> 562599.2 | D24: {=C24*Rendimento_Carteira} -> 5625.992
A25: 30 | B25: Quanto em 30 Anos ? | C25: =FV($D$16,$A25*12,$D$14*-1) -> 2161084.8 | D25: {=C25*Rendimento_Carteira} -> 21610.848
B28: PERFIL | C28: Agressivo
B29: VALOR A SER INVESTIDO POR MÊS | C29: =D14 -> 500
B31: TIPO DE FII | C31: Percentual Sugerido | D31: Valores
B32: PAPEL | C32: =VLOOKUP($C$28&"-"&B32,Auxiliar!B:E,4,FALSE) -> 0.5 | D32: =C32*$C$29 -> 250
B33: TIJOLO | C33: =VLOOKUP($C$28&"-"&B33,Auxiliar!B:E,4,FALSE) -> 0.1 | D33: =C33*$C$29 -> 50
B34: HÍBRIDOS | C34: =VLOOKUP($C$28&"-"&B34,Auxiliar!B:E,4,FALSE) -> 0.05 | D34: =C34*$C$29 -> 25
B35: FOFs | C35: =VLOOKUP($C$28&"-"&B35,Auxiliar!B:E,4,FALSE) -> 0.05 | D35: =C35*$C$29 -> 25
B36: DESENVOLVIMENTO | C36: =VLOOKUP($C$28&"-"&B36,Auxiliar!B:E,4,FALSE) -> 0.2 | D36: =C36*$C$29 -> 100
B37: HOTELARIAS | C37: =VLOOKUP($C$28&"-"&B37,Auxiliar!B:E,4,FALSE) -> 0.1 | D37: =C37*$C$29 -> 50
D38: 200
